docx2csv/__init__.py
docx2csv/converter.py
docx2csv-0.1.0.data/scripts/docx2csv
docx2csv-0.1.0.dist-info/DESCRIPTION.rst
docx2csv-0.1.0.dist-info/METADATA
docx2csv-0.1.0.dist-info/RECORD
docx2csv-0.1.0.dist-info/WHEEL
docx2csv-0.1.0.dist-info/metadata.json
docx2csv-0.1.0.dist-info/top_level.txt
