Metadata-Version: 2.0
Name: docx2csv
Version: 0.1.0
Summary: Extracts tables from .docx files and saves them as csv or xlsx
Home-page: https://github.com/ivbeg/docx2csv
Author: Ivan Begtin
Author-email: ivan@begtin.tech
License: BSD
Keywords: docx converter tables
Platform: UNKNOWN
Classifier: Development Status :: 2 - Pre-Alpha
Classifier: Intended Audience :: Developers
Classifier: License :: OSI Approved :: BSD License
Classifier: Natural Language :: English
Classifier: Programming Language :: Python :: 3
Classifier: Programming Language :: Python :: 3.3
Classifier: Programming Language :: Python :: 3.4
Classifier: Programming Language :: Python :: 3.5
Classifier: Programming Language :: Python :: 3.6
Classifier: Programming Language :: Python :: Implementation :: CPython
Classifier: Programming Language :: Python :: Implementation :: PyPy
Requires-Dist: click
Requires-Dist: python-docx
Requires-Dist: xlwt
Requires-Dist: openpyxl
